<layer>
  <name>a__54_w_divsup_pipe_ew</name>
  <id>LayerInfoImpl--7fad4f3e:1791c31c59c:-7f3b</id>
  <type>VECTOR</type>
  <defaultStyle>
    <id>StyleInfoImpl--7fad4f3e:1791c31c59c:-7e9f</id>
  </defaultStyle>
  <resource class="featureType">
    <id>FeatureTypeInfoImpl--7fad4f3e:1791c31c59c:-7f3c</id>
  </resource>
  <attribution>
    <logoWidth>0</logoWidth>
    <logoHeight>0</logoHeight>
  </attribution>
  <dateCreated>2021-04-29 06:49:23.898 UTC</dateCreated>
  <dateModified>2021-04-30 03:24:44.993 UTC</dateModified>
</layer>