<layer>
  <name>a__54_lu_rid9</name>
  <id>LayerInfoImpl--7fad4f3e:1791c31c59c:-7f45</id>
  <type>VECTOR</type>
  <defaultStyle>
    <id>StyleInfoImpl--7fad4f3e:1791c31c59c:-7eaa</id>
  </defaultStyle>
  <resource class="featureType">
    <id>FeatureTypeInfoImpl--7fad4f3e:1791c31c59c:-7f46</id>
  </resource>
  <attribution>
    <logoWidth>0</logoWidth>
    <logoHeight>0</logoHeight>
  </attribution>
  <dateCreated>2021-04-29 06:48:27.757 UTC</dateCreated>
  <dateModified>2021-04-30 03:23:41.477 UTC</dateModified>
</layer>