<GeoServerTileLayer>
  <id>LayerInfoImpl--6870269b:17ff284d66d:-69c2</id>
  <enabled>true</enabled>
  <inMemoryCached>true</inMemoryCached>
  <name>CM:zoning</name>
  <mimeFormats>
    <string>image/png</string>
    <string>image/jpeg</string>
  </mimeFormats>
  <gridSubsets>
    <gridSubset>
      <gridSetName>EPSG:900913</gridSetName>
      <extent>
        <coords>
          <double>1.0912886254173065E7</double>
          <double>1948895.6059198873</double>
          <double>1.1088367748813616E7</double>
          <double>2290597.4971231096</double>
        </coords>
      </extent>
    </gridSubset>
    <gridSubset>
      <gridSetName>EPSG:4326</gridSetName>
      <extent>
        <coords>
          <double>98.03212515981498</double>
          <double>17.24098810292643</double>
          <double>99.60850224697242</double>
          <double>20.148216502559073</double>
        </coords>
      </extent>
    </gridSubset>
  </gridSubsets>
  <metaWidthHeight>
    <int>4</int>
    <int>4</int>
  </metaWidthHeight>
  <expireCache>0</expireCache>
  <expireClients>0</expireClients>
  <parameterFilters>
    <styleParameterFilter>
      <key>STYLES</key>
      <defaultValue></defaultValue>
      <availableStyles class="sorted-set"/>
      <defaultStyle>CM:38__Zoning</defaultStyle>
    </styleParameterFilter>
  </parameterFilters>
  <gutter>0</gutter>
</GeoServerTileLayer>