<layer>
  <name>a__02_amphoe_eec</name>
  <id>LayerInfoImpl--7fad4f3e:1791c31c59c:-7ff6</id>
  <type>VECTOR</type>
  <defaultStyle>
    <id>StyleInfoImpl-52dccc4f:17a86e41afa:-7d0c</id>
  </defaultStyle>
  <styles class="linked-hash-set">
    <style>
      <id>StyleInfoImpl-52dccc4f:17a86e41afa:-7d0c</id>
    </style>
  </styles>
  <resource class="featureType">
    <id>FeatureTypeInfoImpl--7fad4f3e:1791c31c59c:-7ff8</id>
  </resource>
  <attribution>
    <logoWidth>0</logoWidth>
    <logoHeight>0</logoHeight>
  </attribution>
  <dateCreated>2021-04-29 06:07:17.38 UTC</dateCreated>
  <dateModified>2021-07-22 03:37:18.964 UTC</dateModified>
</layer>